setup.py
lambda_agent_utils/__init__.py
lambda_agent_utils/input_handler.py
lambda_agent_utils/response_handler.py
lambda_agent_utils.egg-info/PKG-INFO
lambda_agent_utils.egg-info/SOURCES.txt
lambda_agent_utils.egg-info/dependency_links.txt
lambda_agent_utils.egg-info/requires.txt
lambda_agent_utils.egg-info/top_level.txt