Metadata-Version: 2.1
Name: lambda-agent-utils
Version: 1.0.5
Summary: Lambda utils
Home-page: UNKNOWN
Author: Pradeep
Author-email: pradeep@incaendo.com
License: MIT
Platform: UNKNOWN
